pycurrency_convertor/__init__.py
pycurrency_convertor-0.0.1.dist-info/METADATA
pycurrency_convertor-0.0.1.dist-info/RECORD
pycurrency_convertor-0.0.1.dist-info/WHEEL
pycurrency_convertor-0.0.1.dist-info/top_level.txt
