Metadata-Version: 2.1
Name: pycurrency-convertor
Version: 0.0.1
Summary: A python package to convert currencyt
Home-page: https://github.com/vaibhavsingh97/pycurrency-convertor
Author: Vaibhav Singh
Author-email: author@vaibhavsingh97.com
License: UNKNOWN
Platform: UNKNOWN
Classifier: Programming Language :: Python :: 3
Classifier: License :: OSI Approved :: MIT License
Classifier: Operating System :: OS Independent
